{
  "id": "c6232d81-89db-4cf5-b5ff-6859ddc6c603",
  "prevId": "debc95f8-96bc-42a9-be20-1d30b3c8e621",
  "version": "7",
  "dialect": "postgresql",
  "tables": {
    "public.tarots": {
      "name": "tarots",
      "schema": "",
      "columns": {
        "id": {
          "name": "id",
          "type": "serial",
          "primaryKey": true,
          "notNull": true
        },
        "name": {
          "name": "name",
          "type": "varchar(10)",
          "primaryKey": false,
          "notNull": true
        },
        "element": {
          "name": "element",
          "type": "tarot_element_type",
          "typeSchema": "public",
          "primaryKey": false,
          "notNull": true
        },
        "image_path": {
          "name": "image_path",
          "type": "text",
          "primaryKey": false,
          "notNull": true
        }
      },
      "indexes": {},
      "foreignKeys": {},
      "compositePrimaryKeys": {},
      "uniqueConstraints": {},
      "policies": {},
      "checkConstraints": {},
      "isRLSEnabled": false
    },
    "public.user_social_accounts": {
      "name": "user_social_accounts",
      "schema": "",
      "columns": {
        "id": {
          "name": "id",
          "type": "serial",
          "primaryKey": true,
          "notNull": true
        },
        "user_id": {
          "name": "user_id",
          "type": "integer",
          "primaryKey": false,
          "notNull": true
        },
        "provider": {
          "name": "provider",
          "type": "social_account_provider",
          "typeSchema": "public",
          "primaryKey": false,
          "notNull": true
        },
        "provider_id": {
          "name": "provider_id",
          "type": "varchar(255)",
          "primaryKey": false,
          "notNull": true
        },
        "email": {
          "name": "email",
          "type": "varchar(255)",
          "primaryKey": false,
          "notNull": true
        },
        "created_at": {
          "name": "created_at",
          "type": "timestamp",
          "primaryKey": false,
          "notNull": false,
          "default": "now()"
        },
        "updated_at": {
          "name": "updated_at",
          "type": "timestamp",
          "primaryKey": false,
          "notNull": false,
          "default": "now()"
        }
      },
      "indexes": {},
      "foreignKeys": {
        "user_social_accounts_user_id_users_id_fk": {
          "name": "user_social_accounts_user_id_users_id_fk",
          "tableFrom": "user_social_accounts",
          "tableTo": "users",
          "columnsFrom": [
            "user_id"
          ],
          "columnsTo": [
            "id"
          ],
          "onDelete": "cascade",
          "onUpdate": "no action"
        }
      },
      "compositePrimaryKeys": {},
      "uniqueConstraints": {},
      "policies": {},
      "checkConstraints": {},
      "isRLSEnabled": false
    },
    "public.users": {
      "name": "users",
      "schema": "",
      "columns": {
        "id": {
          "name": "id",
          "type": "serial",
          "primaryKey": true,
          "notNull": true
        },
        "name": {
          "name": "name",
          "type": "varchar(255)",
          "primaryKey": false,
          "notNull": true
        },
        "email": {
          "name": "email",
          "type": "varchar(255)",
          "primaryKey": false,
          "notNull": true
        },
        "password": {
          "name": "password",
          "type": "text",
          "primaryKey": false,
          "notNull": false
        },
        "birth_date": {
          "name": "birth_date",
          "type": "date",
          "primaryKey": false,
          "notNull": false
        },
        "gender": {
          "name": "gender",
          "type": "gender",
          "typeSchema": "public",
          "primaryKey": false,
          "notNull": false
        },
        "email_verified_at": {
          "name": "email_verified_at",
          "type": "timestamp",
          "primaryKey": false,
          "notNull": false
        },
        "created_at": {
          "name": "created_at",
          "type": "timestamp",
          "primaryKey": false,
          "notNull": false,
          "default": "now()"
        },
        "updated_at": {
          "name": "updated_at",
          "type": "timestamp",
          "primaryKey": false,
          "notNull": false,
          "default": "now()"
        }
      },
      "indexes": {},
      "foreignKeys": {},
      "compositePrimaryKeys": {},
      "uniqueConstraints": {
        "users_email_unique": {
          "name": "users_email_unique",
          "nullsNotDistinct": false,
          "columns": [
            "email"
          ]
        }
      },
      "policies": {},
      "checkConstraints": {},
      "isRLSEnabled": false
    }
  },
  "enums": {
    "public.gender": {
      "name": "gender",
      "schema": "public",
      "values": [
        "male",
        "female",
        "other"
      ]
    },
    "public.social_account_provider": {
      "name": "social_account_provider",
      "schema": "public",
      "values": [
        "google",
        "facebook"
      ]
    },
    "public.tarot_element_type": {
      "name": "tarot_element_type",
      "schema": "public",
      "values": [
        "fire",
        "water",
        "air",
        "earth"
      ]
    }
  },
  "schemas": {},
  "sequences": {},
  "roles": {},
  "policies": {},
  "views": {},
  "_meta": {
    "columns": {},
    "schemas": {},
    "tables": {}
  }
}